test_poetry_deps/__init__.py
test_poetry_deps/deps.py
test_poetry_deps-0.1.0.dist-info/WHEEL
test_poetry_deps-0.1.0.dist-info/METADATA
test_poetry_deps-0.1.0.dist-info/RECORD
