Metadata-Version: 2.1
Name: test-poetry-deps
Version: 0.1.0
Summary: 
Author: Skylar Kerzner
Author-email: skerzner@community.com
Requires-Python: >=3.8,<3.9
Classifier: Programming Language :: Python :: 3
Classifier: Programming Language :: Python :: 3.8
Requires-Dist: emoji (>=1.6.1,<2.0.0)
Requires-Dist: numpy (>=1.21.4,<2.0.0)
Requires-Dist: pandas (>=1.3.4,<2.0.0)
